plinkformatter/__init__.py
plinkformatter/exceptions.py
plinkformatter/generate_pheno_plink.py
plinkformatter/generate_pheno_plink_fast.py
plinkformatter/plink_utils.py
plinkformatter/utils.py
plinkformatter-0.1.77.dist-info/METADATA
plinkformatter-0.1.77.dist-info/WHEEL
plinkformatter-0.1.77.dist-info/RECORD
