Metadata-Version: 2.1
Name: plinkformatter
Version: 0.1.77
Summary: 
Author: nick-sebasco
Author-email: nicksebasco.jax@gmail.com
Requires-Python: >=3.9,<4.0
Classifier: Programming Language :: Python :: 3
Classifier: Programming Language :: Python :: 3.9
Classifier: Programming Language :: Python :: 3.10
Classifier: Programming Language :: Python :: 3.11
Classifier: Programming Language :: Python :: 3.12
Requires-Dist: joblib (>=1.4.2,<2.0.0)
Requires-Dist: numpy (>=1.26.4,<2.0.0)
Requires-Dist: pandas (>=2.2.2,<3.0.0)
Requires-Dist: pyarrow (>=21.0.0,<22.0.0)
Requires-Dist: pytest (>=8.2.2,<9.0.0)
Requires-Dist: scipy (>=1.13.1,<2.0.0)
